hackcqooc/__init__.py
hackcqooc/api_url.py
hackcqooc/core.py
hackcqooc/msg.py
hackcqooc/processor.py
hackcqooc/request.py
hackcqooc/test.py
hackcqooc/user.py
hackcqooc-0.0.12.dist-info/METADATA
hackcqooc-0.0.12.dist-info/WHEEL
hackcqooc-0.0.12.dist-info/RECORD
