Metadata-Version: 2.1
Name: hackcqooc
Version: 0.0.12
Summary: 一个重庆高校在线开放课程平台自动化工具包。
Author-email: Fatpandac <i@fatpandac.com>
License: MIT
Requires-Python: >=3.8
Requires-Dist: js2py~=0.74
Requires-Dist: requests~=2.30.0
